blp/__init__.py
blp/blp.py
blp/test/__init__.py
blp/test/test_blp.py
blp-0.0.3.dist-info/LICENSE
blp-0.0.3.dist-info/METADATA
blp-0.0.3.dist-info/WHEEL
blp-0.0.3.dist-info/top_level.txt
blp-0.0.3.dist-info/RECORD
