Metadata-Version: 2.1
Name: blp
Version: 0.0.3
Summary: Pythonic interface for Bloomberg Open API
Home-page: https://github.com/matthewgilbert/blp
Author-email: matthew.gilbert12@gmail.com
License: MIT
Classifier: Programming Language :: Python :: 3
Classifier: License :: OSI Approved :: MIT License
Classifier: Operating System :: OS Independent
Requires-Python: >=3.6
License-File: LICENSE
Requires-Dist: pandas
